odoo/addons/sms_global_digital/README.rst
odoo/addons/sms_global_digital/__init__.py
odoo/addons/sms_global_digital/__manifest__.py
odoo/addons/sms_global_digital/i18n/pt.po
odoo/addons/sms_global_digital/i18n/sms_global_digital.pot
odoo/addons/sms_global_digital/models/__init__.py
odoo/addons/sms_global_digital/models/iap_account.py
odoo/addons/sms_global_digital/models/sms_api.py
odoo/addons/sms_global_digital/models/sms_sms.py
odoo/addons/sms_global_digital/readme/CONFIGURE.rst
odoo/addons/sms_global_digital/readme/CONTRIBUTORS.rst
odoo/addons/sms_global_digital/readme/DESCRIPTION.rst
odoo/addons/sms_global_digital/readme/USAGE.rst
odoo/addons/sms_global_digital/static/description/icon.png
odoo/addons/sms_global_digital/static/description/index.html
odoo/addons/sms_global_digital/views/iap_account_views.xml
odoo/addons/sms_global_digital/views/res_config_settings_views.xml
odoo14_addon_sms_global_digital-14.0.1.0.1.dev6.dist-info/METADATA
odoo14_addon_sms_global_digital-14.0.1.0.1.dev6.dist-info/WHEEL
odoo14_addon_sms_global_digital-14.0.1.0.1.dev6.dist-info/top_level.txt
odoo14_addon_sms_global_digital-14.0.1.0.1.dev6.dist-info/RECORD
