Metadata-Version: 2.1
Name: odoo14-addon-sms-global-digital
Version: 14.0.1.0.1.dev6
Summary: Send SMS messages using the Global Digital API
Home-page: https://github.com/OCA/l10n-portugal
Author: Exo Software,Odoo Community Association (OCA)
Author-email: support@odoo-community.org
License: AGPL-3
Platform: UNKNOWN
Classifier: Programming Language :: Python
Classifier: Framework :: Odoo
Classifier: Framework :: Odoo :: 14.0
Classifier: License :: OSI Approved :: GNU Affero General Public License v3
Requires-Python: >=3.6
Requires-Dist: odoo14-addon-base-phone
Requires-Dist: odoo14-addon-iap-alternative-provider
Requires-Dist: odoo <14.1dev,>=14.0a
